servermanager/__init__.py
servermanager/app.py
servermanager/auth.py
servermanager/graph copy.py
servermanager/graph.py
servermanager/info.py
servermanager/requirements.txt
servermanager/run.py
servermanager/wsgi.py
servermanager/graphs/cpu_usage.svg
servermanager/graphs/cpu_usage_1.svg
servermanager/graphs/cpu_usage_2.svg
servermanager/graphs/memory_usage_1.svg
servermanager/scripts/jquery.js
servermanager/scripts/proc.js
servermanager/scripts/script.js
servermanager/scripts/script.js.old
servermanager/scripts/script.js.old.new
servermanager/scripts/settings.js
servermanager/settings/settings.json
servermanager/styles/style.css
servermanager/templates/dashboard.html
servermanager/templates/dashboard.html.old
servermanager/templates/index.html
servermanager/templates/login.html
servermanager/templates/login.html.old
servermanager/templates/processes.html
servermanager/templates/settings.html
server_manager-0.0.38.dist-info/METADATA
server_manager-0.0.38.dist-info/WHEEL
server_manager-0.0.38.dist-info/entry_points.txt
server_manager-0.0.38.dist-info/licenses/LICENSE
server_manager-0.0.38.dist-info/RECORD
